trytond/modules/health_ntd/COPYING
trytond/modules/health_ntd/README.rst
trytond/modules/health_ntd/__init__.py
trytond/modules/health_ntd/health_ntd.py
trytond/modules/health_ntd/pyproject.toml
trytond/modules/health_ntd/tests/__init__.py
trytond/modules/health_ntd/tests/test_health_ntd.py
trytond/modules/health_ntd/tryton.cfg
gnuhealth_ntd-5.0.1.dist-info/METADATA
gnuhealth_ntd-5.0.1.dist-info/WHEEL
gnuhealth_ntd-5.0.1.dist-info/licenses/COPYING
gnuhealth_ntd-5.0.1.dist-info/RECORD
