Metadata-Version: 2.4
Name: gnuhealth-ntd
Version: 5.0.1
Summary: Neglected Tropical Diseases -NTD- core package for GNU Health
License: GPL-3.0-or-later
License-File: COPYING
Keywords: health,NTD,HIS,eHealth,gnuhealth
Author: GNU Solidario
Author-email: health@gnusolidario.org
Maintainer: Luis Falcon
Maintainer-email: falcon@gnuhealth.org
Requires-Python: >=3.10,<3.15
Classifier: Development Status :: 5 - Production/Stable
Classifier: Environment :: Plugins
Classifier: Framework :: Tryton
Classifier: Intended Audience :: Developers
Classifier: Intended Audience :: Healthcare Industry
Classifier: License :: OSI Approved :: GNU General Public License v3 or later (GPLv3+)
Classifier: Natural Language :: English
Classifier: Operating System :: OS Independent
Classifier: Programming Language :: Python :: 3
Classifier: Programming Language :: Python :: 3.10
Classifier: Programming Language :: Python :: 3.11
Classifier: Programming Language :: Python :: 3.12
Classifier: Programming Language :: Python :: 3.13
Classifier: Programming Language :: Python :: 3.14
Classifier: Topic :: Scientific/Engineering :: Bio-Informatics
Classifier: Topic :: Scientific/Engineering :: Medical Science Apps.
Requires-Dist: gnuhealth-lab (>=5.0.0,<5.1)
Project-URL: Bug Tracker, https://codeberg.org/gnuhealth/his/issues
Project-URL: Documentation, https://docs.gnuhealth.org
Project-URL: Homepage, https://www.gnuhealth.org
Project-URL: Repository, https://codeberg.org/gnuhealth/his
